Workbook
Name rendimento_carteira: Rendimentos!$D$6:$D$6

Sheet Rendimentos
B4: Configurações
B5: Salário | D5: 1200
B6: Rendimento da carteira | D6: 0.01
B7: Sugestão de investimento | D7: =D5*30% -> 360
B11: Investimento mensal
B12: Quanto investir por mês? | D12: =D7 -> 360
B13: Por quantos anos? | D13: 20
B14: Taxa de redimentos mensal? | D14: 0.012
B15: Patrimonio aculmulado? | D15: =FV(D14,D13*12,-1*D12) -> 495344.58
B16: Dividendos mensais? | D16: =D15*D6 -> 4953.4458
B18: Cenários | D18: Rendimentos
A19: 2 | B19: Quanto em 2 anos? | C19: =FV($D$14,$A19*12,$D$12*-1) -> 9944.1841 | D19: {=C19*rendimento_carteira} -> 99.441841
A20: 5 | B20: Quanto em 5 anos? | C20: =FV($D$14,$A20*12,$D$12*-1) -> 31369.418 | D20: {=C20*rendimento_carteira} -> 313.69418
A21: 9 | B21: Quanto em 9 anos? | C21: =FV($D$14,$A21*12,$D$12*-1) -> 78796.921 | D21: {=C21*rendimento_carteira} -> 787.96921
A22: 10 | B22: Quanto em 10 anos? | C22: =FV($D$14,$A22*12,$D$12*-1) -> 95540.182 | D22: {=C22*rendimento_carteira} -> 955.40182
A23: 15 | B23: Quanto em 15 anos? | C23: =FV($D$14,$A23*12,$D$12*-1) -> 226810.93 | D23: {=C23*rendimento_carteira} -> 2268.1093
A24: 20 | B24: Quanto em 20 anos? | C24: =FV($D$14,$A24*12,$D$12*-1) -> 495344.58 | D24: {=C24*rendimento_carteira} -> 4953.4458
A25: 30 | B25: Quanto em 30 anos? | C25: =FV($D$14,$A25*12,$D$12*-1) -> 2168395.1 | D25: {=C25*rendimento_carteira} -> 21683.951
B28: PERFIL | D28: Agressivo
B29: VALOR INVESTIDO POR MÊS | D29: =D7 -> 360
B32: TIPOS DE FII | C32: PERCENTUAL SUGERIDO | D32: VALORES
B33: PAPEL | C33: =VLOOKUP($D$28&"-"&B33,Apoio!A3:D21,4,FALSE) -> 0.5 | D33: =$D$29*C33 -> 180
B34: TIJOLO | C34: =VLOOKUP($D$28&"-"&B34,Apoio!A4:D22,4,FALSE) -> 0.1 | D34: =$D$29*C34 -> 36
B35: HÍBRIDO | C35: =VLOOKUP($D$28&"-"&B35,Apoio!A5:D23,4,FALSE) -> 0.05 | D35: =$D$29*C35 -> 18
B36: FOFs | C36: =VLOOKUP($D$28&"-"&B36,Apoio!A6:D24,4,FALSE) -> 0.05 | D36: =$D$29*C36 -> 18
B37: DESENVOLVIMENTO | C37: =VLOOKUP($D$28&"-"&B37,Apoio!A7:D25,4,FALSE) -> 0.2 | D37: =$D$29*C37 -> 72
B38: HOTELARIAS | C38: =VLOOKUP($D$28&"-"&B38,Apoio!A8:D26,4,FALSE) -> 0.1 | D38: =$D$29*C38 -> 36
D39: =SUM(D33:D38) -> 360

Sheet Apoio
A3: CHAVE | B3: PERFIL | C3: TIPOS DE FII | D3: PORCENTAGEM (%)
A4: =B4&"-"&C4 -> Conservador-PAPEL | B4: Conservador | C4: PAPEL | D4: 0.3
A5: =B5&"-"&C5 -> Conservador-TIJOLO | B5: Conservador | C5: TIJOLO | D5: 0.5
A6: =B6&"-"&C6 -> Conservador-HÍBRIDO | B6: Conservador | C6: HÍBRIDO | D6: 0.1
A7: =B7&"-"&C7 -> Conservador-FOFs | B7: Conservador | C7: FOFs | D7: 0.1
A8: =B8&"-"&C8 -> Conservador-DESENVOLVIMENTO | B8: Conservador | C8: DESENVOLVIMENTO | D8: 0
A9: =B9&"-"&C9 -> Conservador-HOTELARIAS | B9: Conservador | C9: HOTELARIAS | D9: 0
A10: =B10&"-"&C10 -> Moderado-PAPEL | B10: Moderado | C10: PAPEL | D10: 0.32
A11: =B11&"-"&C11 -> Moderado-TIJOLO | B11: Moderado | C11: TIJOLO | D11: 0.4
A12: =B12&"-"&C12 -> Moderado-HÍBRIDO | B12: Moderado | C12: HÍBRIDO | D12: 0.08
A13: =B13&"-"&C13 -> Moderado-FOFs | B13: Moderado | C13: FOFs | D13: 0.1
A14: =B14&"-"&C14 -> Moderado-DESENVOLVIMENTO | B14: Moderado | C14: DESENVOLVIMENTO | D14: 0.1
A15: =B15&"-"&C15 -> Moderado-HOTELARIAS | B15: Moderado | C15: HOTELARIAS | D15: 0.1
... A21: =B21&"-"&C21 -> Agressivo-HOTELARIAS | B21: Agressivo | C21: HOTELARIAS | D21: 0.1

Sheet TÍTULAR
C3: 1. DADOS DO TÍTULAR
C4: preencha abaixo com os dados do títular
C7: NOME | D7: Ryland Grace
C8: CPF | D8: 875.963.257-13
C9: NASCIMENTO | D9: 23330
C10: TÍTULO DE ELEITOR | D10: 14759638-5
C11: CÔNJUGE | D11: Marcelina
C12: RUA | D12: Rua Tiradentes
C13: RUA ABREVIADA | D13: Rua Tiradentes
C14: CEP | D14: 098045-9
C15: TELEFONE | D15: (11)95863-8512
C16: CELULAR | D16: 3546-9621
C17: E-MAIL | D17: grace.ryland@gmail.com
C18: HOUVE ALTERAÇÕES NA ENTREGA ANTERIOR | D18: NÃO
C19: DEPENDENTE CÔNJUGE | D19: NÃO
C20: RESIDENTE DO EXTERIOR | D20: SIM

Sheet INFORMES
C3: 2. INFORMES DE RENDIMENTO BANCÁRIO
C4: preencha abaixo com os dados do títular
C6: TOTAL
C7: =SUM(D11,D17,D23) -> 14575298
C9: 1º banco
C10: BANCO | D10: 341 - Itaú Unibanco
C11: VALOR ATUAL | D11: 3005200
C12: ANEXO | D12: recibo_itau_2034.pdf
C15: 2º banco
C16: BANCO | D16: 1 - Banco do Brasil
C17: VALOR ATUAL | D17: 10000
C18: ANEXO | D18: recibo_bb_2034.pdf
C21: 3º banco
C22: BANCO | D22: 74 - Banco J. Safra
C23: VALOR ATUAL | D23: 11560098
C24: ANEXO | D24: recibo_safra_2034.pdf

Sheet NOTAS
C3: 3. NOTAS BANCÁRIAS OU EXTRATO DE HOLERITES
C4: são todos os valores de entrada mês a mês de receita
C7: ENTRADAS
C8: DATA | D8: CATEGORIA | E8: VALOR
C9: 46030 | D9: CNPJ | E9: 50000
C10: 46050 | D10: HOLERITE | E10: 85
C11: 46051 | D11: FREELANCER | E11: 899.99
C12: 46052 | D12: HOLERITE | E12: 78.95
C13: 46053 | D13: HOLERITE | E13: 10000
C14: 46054 | D14: FREELANCER | E14: 63.96
C15: 46055 | D15: CNPJ | E15: 7841
C16: 46056 | D16: HOLERITE | E16: 49.89

Sheet TABELAS
A1: BANCOS
A2: 1 - Banco do Brasil
A3: 102 - XP Investimentos CCTVM S.A.
A4: 104 - Caixa Econômica Federal
A5: 119 - Banco Western Union do Brasil
A6: 184 - Banco Itaú BBA S.A.
A7: 197 - Stone Pagamentos
A8: 208 - Banco BTG Pactual
A9: 212 - Banco Original
A10: 218 - Banco Bonsucesso
A11: 229 - Banco Cruzeiro do Sul
A12: 237 - Banco Bradesco
... A51: 82 - Banco Topázio
